LICENSE.txt
setup.cfg
setup.py
ml360nlppre/__init__.py
ml360nlppre/ml360nlppre.py
ml360nlppre.egg-info/PKG-INFO
ml360nlppre.egg-info/SOURCES.txt
ml360nlppre.egg-info/dependency_links.txt
ml360nlppre.egg-info/requires.txt
ml360nlppre.egg-info/top_level.txt