Metadata-Version: 2.1
Name: ml360nlppre
Version: 0.0.9
Summary: NLP Preprocessing library
Home-page:  
Download-URL:  
Author: Karthick Nagaraj
Author-email: karthick12nagaraj@gmail.com
License: MIT
Keywords: NLP,Preprocessing,spacy,NLTK,Transformers,Bert
Platform: UNKNOWN
Classifier: Development Status :: 3 - Alpha
Classifier: Intended Audience :: Developers
Classifier: Topic :: Software Development :: Build Tools
Classifier: License :: OSI Approved :: MIT License
Classifier: Programming Language :: Python :: 3
Classifier: Programming Language :: Python :: 3.4
Classifier: Programming Language :: Python :: 3.5
Classifier: Programming Language :: Python :: 3.6
License-File: LICENSE.txt
